[
  {
    "id": "1",
    "userId": null,
    "timestamp": 1515467007,
    "subject": null,
    "name": "Q",
    "email": null,
    "trip": "!UW.yye1fxo",
    "text": "TRUTH belongs with the PEOPLE.\nQ\n",
    "images": [],
    "threadId": "1",
    "source": "8chan_greatawakening",
    "link": "https://8ch.net//greatawakening/res/1.html#1"
  },
  {
    "id": "4",
    "userId": null,
    "timestamp": 1515472178,
    "subject": null,
    "name": "Q",
    "email": null,
    "trip": "!UW.yye1fxo",
    "text": "IMPORTANT:\nNO private comms past/present/future.\nNO comms made outside of this platform.\nAny claims that contradict the above should be considered FAKE NEWS and disregarded immediately. \nWHERE WE GO ONE, WE GO ALL.\nPATRIOTS.\nQ\n",
    "images": [],
    "threadId": "1",
    "source": "8chan_greatawakening",
    "link": "https://8ch.net//greatawakening/res/1.html#4"
  },
  {
    "id": "5",
    "userId": null,
    "timestamp": 1515472775,
    "subject": null,
    "name": "Q",
    "email": null,
    "trip": "!UW.yye1fxo",
    "text": "Future dumps here.\nSecured.\nInteraction to continue on dedicated /research/ board.\nSuggest new board created.\nCurrent BO’s claiming private comms and self promoting.\nPatriots point - we will follow.\nQ\n",
    "images": [],
    "threadId": "1",
    "source": "8chan_greatawakening",
    "link": "https://8ch.net//greatawakening/res/1.html#5"
  },
  {
    "id": "7",
    "userId": null,
    "timestamp": 1515896633,
    "subject": null,
    "name": "Q",
    "email": null,
    "trip": "!UW.yye1fxo",
    "text": "SEC TEST.\n1/13/18\n",
    "images": [],
    "threadId": "1",
    "source": "8chan_greatawakening",
    "link": "https://8ch.net//greatawakening/res/1.html#7"
  },
  {
    "id": "8",
    "userId": null,
    "timestamp": 1515899378,
    "subject": null,
    "name": "Q",
    "email": null,
    "trip": "!UW.yye1fxo",
    "text": "BIG news week?\nFuture proves past. \nWhat news was unlocked?\nDo you believe in coincidences?\n>U1\nWhat public disclosure occurred re: U1?\n>DEFCON 1 [non-nuke FALSE]\nCOMMAND?\nWHY?\nNECESSARY?\nNO SUCH AGENCY.\nWhere did POTUS stop [post] ASIA?\nIT WAS NECESSARY.\nFOR GOD &amp; COUNTRY.\nIT WAS NECESSARY.\nNO OTHER VEHICLE TO REGAIN ENTRY.\n:[AGAIN] direct pre-knowledge. \n:[AGAIN] warning ALERT.\nThink BDT.\n>Shall we play a game?\n>How about a nice game of CHESS?\n_THE_FLOOR_IS_YOURS_\nCOMMAND?\nWHY?\nNECESSARY?\nWHO IS TALKING?\nTHINK BIG.\nTHINK BIGGER.\nTHINK BIGGEST.\n>HAITI FOCUS\nWhy is this relevant?\nWhat comes next?\nCF_BOOM_SHOCK_BYE_\n>ADM R\n[CLAS-239B_TC]\n>\"…Because of the Democrats not being interested in life and safety, DACA has now taken a big step backwards. The Dems will threaten “shutdown,” but what they are really doing is shutting down our military, at a time we need it most. Get smart, MAKE AMERICA GREAT AGAIN!\nWE ARE FIGHTING FOR OUR COUNTRY!\"\nFOCUS on POTUS' Tweet above.\nIf D's shutdown the gov't - what happens to the US MILITARY? \nWhat specifically occurs? \nThink budget.\nWhy is this relevant? \n[CLAS_EO_        ][2]\n>Missing 1\n>Missing 2\n>Missing 3\nFIND missing [3].\nFuture proves past.\nNOTHING is a coincidence.\nThe MAP is the KEY.\nPLANNED for [3] years.\nCORRUPTION and EVIL DEEP WITHIN.\nEVERYWHERE.\nPATIENCE.\nTHERE IS NO ESCAPE.\nTHERE ARE NO DEALS.\nTREASON AT HIGHEST LEVELS.\nFOREIGN AGENTS WITHIN OUR GOV'T.\nHIGHEST LEVELS.\nTHE PUPPET MASTERS HAVE BEEN REMOVED.\nALL VEHICLES OF DELIVERY REMOVED.\nSTRINGS CUT.\n7TH FLOOR IS NO MORE&gt;FBI/SD\nWE SEE ALL.\nWE HEAR ALL.\nTHE HUNT CONTINUES.\nPRISON.\nDEATH.\n[CLAS_GITMO_    J   z9-A][89]\nRED_RED_\nIRON EAGLE.\nQ\n",
    "images": [],
    "threadId": "1",
    "source": "8chan_greatawakening",
    "link": "https://8ch.net//greatawakening/res/1.html#8"
  },
  {
    "id": "9",
    "userId": null,
    "timestamp": 1515899898,
    "subject": null,
    "name": "Q",
    "email": null,
    "trip": "!UW.yye1fxo",
    "text": "We are FIGHTING for LIFE.\nWe are FIGHTING for GOOD.\nWe are at WAR [@].\nNOT EVERYTHING WILL BE CLEAN.\n[SCARE] NECESSARY EVENT.\nDo you TRUST the US Military?\nDo you TRUST the Chain Of Command?\nHave FAITH - WE ARE IN CONTROL.\nPATRIOTS.\nPATRIOTS DAY.\nHAVE FAITH. \nYOU WERE CHOSEN FOR A REASON.\nYOU ARE BEING PROVIDED THE HIGHEST LEVEL OF INTEL TO EVER BE DROPPED PUBLICLY IN THE HISTORY OF THE WORLD.\nUSE IT - PROTECT AND COMFORT THOSE AROUND YOU.\nWHERE WE GO ONE, WE GO ALL.\nQ\n",
    "images": [],
    "threadId": "1",
    "source": "8chan_greatawakening",
    "link": "https://8ch.net//greatawakening/res/1.html#9"
  },
  {
    "id": "10",
    "userId": null,
    "timestamp": 1515900824,
    "subject": null,
    "name": "Q",
    "email": null,
    "trip": "!UW.yye1fxo",
    "text": "-D_CsTBA_YES[AUTH_H7^pZBVTZ7302-]\n##FLY##\n[OWLS]\nHOT-1_pre_D\nHOT-2_pre_D\nHOT-3+\nHOT-4_TERM_AUTHC-TVFCAZD-837392x\nHOT-5_pre_D\nHOT-6_pre_D\nHOT-7_corr_TAXjV^-293Z\nHOT-8_pre_D\nHOT-9_pre_D\nHOT-10_pre_D\nHOT-11_pre_D\nHOT-12_pre_D\nAS THE WORLD TURNS.\nHAPPY HUNTING.\nP_PERS: WRWY [N1LB][FG&amp;C]\nJeremiah 29:11\nQ\n",
    "images": [],
    "threadId": "1",
    "source": "8chan_greatawakening",
    "link": "https://8ch.net//greatawakening/res/1.html#10"
  },
  {
    "id": "11",
    "userId": null,
    "timestamp": 1515900989,
    "subject": null,
    "name": "Q",
    "email": null,
    "trip": "!UW.yye1fxo",
    "text": "CHECKMATE.\nQ\n",
    "images": [],
    "threadId": "1",
    "source": "8chan_greatawakening",
    "link": "https://8ch.net//greatawakening/res/1.html#11"
  },
  {
    "id": "12",
    "userId": null,
    "timestamp": 1515901539,
    "subject": null,
    "name": "Q",
    "email": null,
    "trip": "!UW.yye1fxo",
    "text": "LOOP CAPITAL.\nCEOs/BODs PAYING TO PLAY.\n>Slush Fund\n>&gt;Hussein [1] $29,000,000 SINGAPORE\n>&gt;We don't say his name [2] $19,000,000 SINGAPORE\n(Why don't we say his name?)\n>&gt;HRC/BC [3] $15,000,000 Banco de MEXICO\n>&gt;NP [4] $8,000,000 Deutsche Bank USA\n……….ON……AND…….&gt;ON…….\nFOLLOW THE MONEY.\nFOCUS on loudest voices in WASH.\nNet Worth? \nReconcile? \nQ\n",
    "images": [],
    "threadId": "1",
    "source": "8chan_greatawakening",
    "link": "https://8ch.net//greatawakening/res/1.html#12"
  },
  {
    "id": "13",
    "userId": null,
    "timestamp": 1515901681,
    "subject": null,
    "name": "Q",
    "email": null,
    "trip": "!UW.yye1fxo",
    "text": "7/10.\nTargeted Kills.\nPower Out.\nFlight re-routes.\nFlight returns.\nRunning.\nPublic awakening. \nMessage spreading wide &amp; far.\nGoodbye @Jack.\nQ\n",
    "images": [],
    "threadId": "1",
    "source": "8chan_greatawakening",
    "link": "https://8ch.net//greatawakening/res/1.html#13"
  },
  {
    "id": "14",
    "userId": null,
    "timestamp": 1515901876,
    "subject": null,
    "name": "Q",
    "email": null,
    "trip": "!UW.yye1fxo",
    "text": "https://en.wikipedia.org/wiki/Marc_Mezvinsky\nMezvinsky was born in Philadelphia, Pennsylvania, and grew up attending a Conservative Jewish synagogue.[2] His parents are both former Democratic members of the U.S. House of Representatives. His father is Edward Mezvinsky (b. 1937), who embezzled more than $10 million from people via both a Ponzi scheme and the advance-fee scams, and was found guilty of fraud in 2001.[3][4][5] His mother is Marjorie Margolies (b. 1942), who was a TV reporter and represented Pennsylvania's 13th District from 1993 to 1995. They declared bankruptcy shortly before Mezvinsky's conviction, and divorced.[6]\nFOLLOW HIM AND FAMILY DOWN THE HOLE TO FIND MORE TRUTH.\nQ\n",
    "images": [],
    "threadId": "1",
    "source": "8chan_greatawakening",
    "link": "https://8ch.net//greatawakening/res/1.html#14"
  },
  {
    "id": "15",
    "userId": null,
    "timestamp": 1515902314,
    "subject": null,
    "name": "Q",
    "email": null,
    "trip": "!UW.yye1fxo",
    "text": "[MONDAY]\nNext Week - BIGGER.\nPUBLIC.\nWe LISTENED [20/80 /&gt;/ 40/60].\nQ\n",
    "images": [],
    "threadId": "1",
    "source": "8chan_greatawakening",
    "link": "https://8ch.net//greatawakening/res/1.html#15"
  },
  {
    "id": "16",
    "userId": null,
    "timestamp": 1515902356,
    "subject": null,
    "name": "Q",
    "email": null,
    "trip": "!UW.yye1fxo",
    "text": "YOU and YOUR FAMILIES are SAFE.\nPROMISE.\nQ\n",
    "images": [],
    "threadId": "1",
    "source": "8chan_greatawakening",
    "link": "https://8ch.net//greatawakening/res/1.html#16"
  },
  {
    "id": "17",
    "userId": null,
    "timestamp": 1515903419,
    "subject": null,
    "name": "Q",
    "email": null,
    "trip": "!UW.yye1fxo",
    "text": "Be READY.\nMSM coming - BIG WAY.\nWe see all.\nWe hear all.\nFIGHT, FIGHT, FIGHT.\nCONSPIRACY push coming.\nMSM LOST CONTROL.\nD LOST SLAVE GRIP.\nD LOST CENTER VOTERS.\nLIBS are MINORITY.\nMSM PROJECTS AS BIG MOVEMENT.\nFAKE NEWS.\n4-6% LOST FOREVER.\nHELLO GEORGE.\nQ\n",
    "images": [],
    "threadId": "1",
    "source": "8chan_greatawakening",
    "link": "https://8ch.net//greatawakening/res/1.html#17"
  },
  {
    "id": "18",
    "userId": null,
    "timestamp": 1515904117,
    "subject": null,
    "name": "Q",
    "email": null,
    "trip": "!UW.yye1fxo",
    "text": "Side-by-Side Posts vs. Actual News.\nShow: Future PROVES Past.\nBIGGER next week.\nQ\n",
    "images": [],
    "threadId": "1",
    "source": "8chan_greatawakening",
    "link": "https://8ch.net//greatawakening/res/1.html#18"
  }
]